{
  "framework": "Z\u00b2 Disulfide Metric Locking",
  "timestamp": "2026-04-18T21:52:31.448821",
  "Z": 5.788810036466141,
  "Z2": 33.510321638291124,
  "theta_Z2_deg": 31.094473452420196,
  "tests": {
    "insulin_b": {
      "sequence": "FVNQHLCGSHLVEALYLVCGERGFFYTPKT",
      "n_cys": 2,
      "cys_positions": [
        6,
        18
      ],
      "predicted_pairs": []
    },
    "lysozyme_like": {
      "n_cys": 8,
      "cys_positions": [
        5,
        29,
        63,
        75,
        79,
        93,
        114,
        126
      ],
      "predicted_pairs": []
    },
    "custom_z2": {
      "sequence": "CAAAAACAAAAACAAAAACAAAAACAAAAACAAAAACAAAAACAAAAAAA",
      "n_cys": 8,
      "cys_positions": [
        0,
        6,
        12,
        18,
        24,
        30,
        36,
        42
      ],
      "predicted_pairs": []
    }
  }
}